cubric_mrs/__init__.py
cubric_mrs/_version.py
cubric_mrs/megapress.py
cubric_mrs/press.py
cubric_mrs/table.py
cubric_mrs/voxel.py
cubric_mrs-0.2.2.dist-info/METADATA
cubric_mrs-0.2.2.dist-info/RECORD
cubric_mrs-0.2.2.dist-info/WHEEL
cubric_mrs-0.2.2.dist-info/entry_points.txt
cubric_mrs-0.2.2.dist-info/top_level.txt
