Metadata-Version: 2.1
Name: cubric-mrs
Version: 0.2.2
Summary: a collection of processing scripts for handling MRS data at CUBRIC
Home-page: https://github.com/bennyrowland/cubric_mrs.git
Author: bennyrowland
Author-email: bennyrowland@mac.com
License: MIT
Platform: UNKNOWN
Classifier: Development Status :: 3 - Alpha
Classifier: Intended Audience :: Science/Research
Classifier: Topic :: Scientific/Engineering :: Medical Science Apps.
Classifier: Topic :: Scientific/Engineering :: Physics
Classifier: License :: OSI Approved :: MIT License
Classifier: Programming Language :: Python :: 3
Classifier: Programming Language :: Python :: 3.2
Classifier: Programming Language :: Python :: 3.3
Classifier: Programming Language :: Python :: 3.4
Classifier: Programming Language :: Python :: 3.5
Requires-Dist: suspect (>=0.3.5)
Requires-Dist: numpy
Requires-Dist: Pillow
Requires-Dist: pyx
Requires-Dist: nibabel
Requires-Dist: nipype
